cornflow_core/__init__.py
cornflow_core/authentication/__init__.py
cornflow_core/authentication/auth.py
cornflow_core/authentication/decorators.py
cornflow_core/authentication/ldap.py
cornflow_core/cli/__init__.py
cornflow_core/cli/generate_from_schema.py
cornflow_core/cli/schema_from_models.py
cornflow_core/cli/tools/__init__.py
cornflow_core/cli/tools/api_generator.py
cornflow_core/cli/tools/endpoint_tools.py
cornflow_core/cli/tools/models_tools.py
cornflow_core/cli/tools/schema_generator.py
cornflow_core/cli/tools/schemas_tools.py
cornflow_core/cli/tools/tools.py
cornflow_core/compress/__init__.py
cornflow_core/compress/compress.py
cornflow_core/constants/__init__.py
cornflow_core/constants/authentication.py
cornflow_core/constants/roles.py
cornflow_core/exceptions/__init__.py
cornflow_core/exceptions/exceptions.py
cornflow_core/messages/__init__.py
cornflow_core/messages/email.py
cornflow_core/models/__init__.py
cornflow_core/models/action.py
cornflow_core/models/meta_models.py
cornflow_core/models/permissions.py
cornflow_core/models/role.py
cornflow_core/models/user.py
cornflow_core/models/user_role.py
cornflow_core/models/view.py
cornflow_core/resources/__init__.py
cornflow_core/resources/log_in.py
cornflow_core/resources/meta_resource.py
cornflow_core/resources/recover_password.py
cornflow_core/resources/sign_up.py
cornflow_core/schemas/__init__.py
cornflow_core/schemas/action.py
cornflow_core/schemas/patch.py
cornflow_core/schemas/permissions.py
cornflow_core/schemas/query.py
cornflow_core/schemas/role.py
cornflow_core/schemas/user.py
cornflow_core/schemas/user_role.py
cornflow_core/schemas/view.py
cornflow_core/shared/__init__.py
cornflow_core/shared/utils.py
cornflow_core/shared/validators.py
cornflow_core/tests/__init__.py
cornflow_core/tests/test_generate_from_schema.py
cornflow_core/tests/test_schema_from_models.py
cornflow_core-0.1.10.dist-info/LICENSE
cornflow_core-0.1.10.dist-info/METADATA
cornflow_core-0.1.10.dist-info/WHEEL
cornflow_core-0.1.10.dist-info/entry_points.txt
cornflow_core-0.1.10.dist-info/top_level.txt
cornflow_core-0.1.10.dist-info/RECORD
