Metadata-Version: 2.1
Name: cornflow-core
Version: 0.1.10
Summary: REST API flask backend components used by cornflow and other REST APIs
Home-page: https://github.com/baobabsoluciones/cornflow
Author: baobab soluciones
Author-email: sistemas@baobabsoluciones.es
License: UNKNOWN
Platform: UNKNOWN
Classifier: Programming Language :: Python :: 3
Classifier: License :: OSI Approved :: MIT License
Classifier: Operating System :: OS Independent
Classifier: Development Status :: 3 - Alpha
Requires-Python: >=3.7
Requires-Dist: click
Requires-Dist: cornflow-client (<=1.0.12)
Requires-Dist: cryptography
Requires-Dist: disposable-email-domains
Requires-Dist: Flask (==2.1.3)
Requires-Dist: flask-apispec
Requires-Dist: Flask-Bcrypt
Requires-Dist: Flask-Compress
Requires-Dist: Flask-RESTful
Requires-Dist: Flask-SQLAlchemy (==2.5.1)
Requires-Dist: ldap3
Requires-Dist: marshmallow
Requires-Dist: PyJWT
Requires-Dist: pytups
Requires-Dist: requests
Requires-Dist: SQLAlchemy (==1.3.21)
Requires-Dist: webargs
Requires-Dist: Werkzeug
